ncu_python_edm/__init__.py
ncu_python_edm/static/README.md
ncu_python_edm/static/description.yaml
ncu_python_edm/static/index.js
ncu_python_edm-0.0.1.dist-info/METADATA
ncu_python_edm-0.0.1.dist-info/WHEEL
ncu_python_edm-0.0.1.dist-info/top_level.txt
ncu_python_edm-0.0.1.dist-info/RECORD
