Metadata-Version: 2.1
Name: ncu-python-edm
Version: 0.0.1
Summary: 我測試一下
Home-page: https://github.com/lairuilin/logger_test
Author: lairuilin
Author-email: kalai850531@g.ncu.edu.tw
License: MIT
Platform: UNKNOWN
Requires-Dist: jupyter
